{
    "data": {
        "findEmojis": [{
                "animated": true,
                "id": "765554189107068950",
                "invite": "zY8US2f",
                "name": "aBES_PensiveParty",
                "__typename": "Emoji"
            }, {
                "animated": false,
                "id": "765554189128433676",
                "invite": "zY8US2f",
                "name": "BES_Cool",
                "__typename": "Emoji"
            }, {
                "animated": false,
                "id": "765554189139968012",
                "invite": "zY8US2f",
                "name": "BES_Eyyy",
                "__typename": "Emoji"
            }, {
                "animated": true,
                "id": "765554189140099113",
                "invite": "zY8US2f",
                "name": "aBES_Hyper",
                "__typename": "Emoji"
            }, {
                "animated": false,
                "id": "765554189140754484",
                "invite": "zY8US2f",
                "name": "BES_Flushed",
                "__typename": "Emoji"
            }, {
                "animated": false,
                "id": "765554189195411478",
                "invite": "zY8US2f",
                "name": "BES_CrySmile",
                "__typename": "Emoji"
            }, {
                "animated": false,
                "id": "765554189202882561",
                "invite": "zY8US2f",
                "name": "BES_Thonk",
                "__typename": "Emoji"
            }, {
                "animated": false,
                "id": "765554189224116256",
                "invite": "zY8US2f",
                "name": "BES_Happy",
                "__typename": "Emoji"
            }, {
                "animated": false,
                "id": "765554189258063923",
                "invite": "zY8US2f",
                "name": "BES_Crazy",
                "__typename": "Emoji"
            }, {
                "animated": false,
                "id": "765554189312720917",
                "invite": "zY8US2f",
                "name": "BES_Kiss",
                "__typename": "Emoji"
            }, {
                "animated": false,
                "id": "765554189329760258",
                "invite": "zY8US2f",
                "name": "BES_StuckOutTongue",
                "__typename": "Emoji"
            }, {
                "animated": false,
                "id": "765554189354401824",
                "invite": "zY8US2f",
                "name": "BES_Nerd",
                "__typename": "Emoji"
            }, {
                "animated": false,
                "id": "765554189370654721",
                "invite": "zY8US2f",
                "name": "BES_Swearing",
                "__typename": "Emoji"
            }, {
                "animated": false,
                "id": "765554189375242262",
                "invite": "zY8US2f",
                "name": "BES_HeartEyes",
                "__typename": "Emoji"
            }, {
                "animated": false,
                "id": "765554189429768233",
                "invite": "zY8US2f",
                "name": "BES_AngryGun",
                "__typename": "Emoji"
            }, {
                "animated": false,
                "id": "765554189434093610",
                "invite": "zY8US2f",
                "name": "BES_Pensive",
                "__typename": "Emoji"
            }, {
                "animated": true,
                "id": "765554189447200809",
                "invite": "zY8US2f",
                "name": "aBES_LennyFace",
                "__typename": "Emoji"
            }, {
                "animated": false,
                "id": "765554189513261057",
                "invite": "zY8US2f",
                "name": "BES_Wave",
                "__typename": "Emoji"
            }, {
                "animated": false,
                "id": "765554189538426910",
                "invite": "zY8US2f",
                "name": "BES_Disguised",
                "__typename": "Emoji"
            }, {
                "animated": false,
                "id": "765554189559922708",
                "invite": "zY8US2f",
                "name": "BES_Dab",
                "__typename": "Emoji"
            }, {
                "animated": false,
                "id": "765554189563854868",
                "invite": "zY8US2f",
                "name": "BES_Clown",
                "__typename": "Emoji"
            }, {
                "animated": false,
                "id": "765554189563985980",
                "invite": "zY8US2f",
                "name": "BES_Halloween",
                "__typename": "Emoji"
            }, {
                "animated": false,
                "id": "765554189567918120",
                "invite": "zY8US2f",
                "name": "BES_F",
                "__typename": "Emoji"
            }, {
                "animated": false,
                "id": "765554189584564224",
                "invite": "zY8US2f",
                "name": "BES_CowboyFlushed",
                "__typename": "Emoji"
            }, {
                "animated": true,
                "id": "765554189584695296",
                "invite": "zY8US2f",
                "name": "aBES_Bounce",
                "__typename": "Emoji"
            }, {
                "animated": false,
                "id": "765554189584695357",
                "invite": "zY8US2f",
                "name": "BES_What",
                "__typename": "Emoji"
            }, {
                "animated": true,
                "id": "765554189589544990",
                "invite": "zY8US2f",
                "name": "aBES_PensiveShake",
                "__typename": "Emoji"
            }, {
                "animated": false,
                "id": "765554189593346068",
                "invite": "zY8US2f",
                "name": "BES_OWO",
                "__typename": "Emoji"
            }, {
                "animated": false,
                "id": "765554189593346088",
                "invite": "zY8US2f",
                "name": "BES_Smile",
                "__typename": "Emoji"
            }, {
                "animated": false,
                "id": "765554189597278208",
                "invite": "zY8US2f",
                "name": "BES_Cry",
                "__typename": "Emoji"
            }, {
                "animated": false,
                "id": "765554189614972929",
                "invite": "zY8US2f",
                "name": "BES_Vomit",
                "__typename": "Emoji"
            }, {
                "animated": false,
                "id": "765554189618642986",
                "invite": "zY8US2f",
                "name": "BES_ThumbsUp",
                "__typename": "Emoji"
            }, {
                "animated": false,
                "id": "765554189619167282",
                "invite": "zY8US2f",
                "name": "BES_SweatSmile",
                "__typename": "Emoji"
            }, {
                "animated": false,
                "id": "765554189622312960",
                "invite": "zY8US2f",
                "name": "BES_ThanosSnap",
                "__typename": "Emoji"
            }, {
                "animated": false,
                "id": "765554189639352320",
                "invite": "zY8US2f",
                "name": "BES_PensiveCowboy",
                "__typename": "Emoji"
            }, {
                "animated": false,
                "id": "765554189639614474",
                "invite": "zY8US2f",
                "name": "BES_StarStruck",
                "__typename": "Emoji"
            }, {
                "animated": false,
                "id": "765554189643284491",
                "invite": "zY8US2f",
                "name": "BES_King",
                "__typename": "Emoji"
            }, {
                "animated": false,
                "id": "765554189648265246",
                "invite": "zY8US2f",
                "name": "BES_Wink",
                "__typename": "Emoji"
            }, {
                "animated": false,
                "id": "765554189672906793",
                "invite": "zY8US2f",
                "name": "BES_Pinching",
                "__typename": "Emoji"
            }, {
                "animated": false,
                "id": "765554189681426472",
                "invite": "zY8US2f",
                "name": "BES_Triumph",
                "__typename": "Emoji"
            }, {
                "animated": false,
                "id": "765554189685882920",
                "invite": "zY8US2f",
                "name": "BES_Sad",
                "__typename": "Emoji"
            }, {
                "animated": false,
                "id": "765554189686276106",
                "invite": "zY8US2f",
                "name": "BES_TipsFedora",
                "__typename": "Emoji"
            }, {
                "animated": false,
                "id": "765554189689421885",
                "invite": "zY8US2f",
                "name": "BES_Unamused",
                "__typename": "Emoji"
            }, {
                "animated": false,
                "id": "765554189727432724",
                "invite": "zY8US2f",
                "name": "BES_Think",
                "__typename": "Emoji"
            }, {
                "animated": false,
                "id": "765554189732282398",
                "invite": "zY8US2f",
                "name": "BES_Salute",
                "__typename": "Emoji"
            }, {
                "animated": false,
                "id": "765554189740670996",
                "invite": "zY8US2f",
                "name": "BES_Monocle",
                "__typename": "Emoji"
            }, {
                "animated": false,
                "id": "765554189774225429",
                "invite": "zY8US2f",
                "name": "BES_Weary",
                "__typename": "Emoji"
            }, {
                "animated": false,
                "id": "765554189781696602",
                "invite": "zY8US2f",
                "name": "BES_Wheeze",
                "__typename": "Emoji"
            }, {
                "animated": false,
                "id": "765554189920501771",
                "invite": "zY8US2f",
                "name": "BES_ThumbsDown",
                "__typename": "Emoji"
            }, {
                "animated": true,
                "id": "771019697411457054",
                "invite": "zY8US2f",
                "name": "aBES_PetTheBread",
                "__typename": "Emoji"
            }, {
                "animated": false,
                "id": "798895086522859570",
                "invite": "zY8US2f",
                "name": "BES_Threaten",
                "__typename": "Emoji"
            }, {
                "animated": false,
                "id": "806241248791887902",
                "invite": "zY8US2f",
                "name": "BES_UWU",
                "__typename": "Emoji"
            }, {
                "animated": false,
                "id": "816103292726673458",
                "invite": "zY8US2f",
                "name": "BES_Sus",
                "__typename": "Emoji"
            }, {
                "animated": false,
                "id": "816103357122609194",
                "invite": "zY8US2f",
                "name": "BES_Moyai",
                "__typename": "Emoji"
            }, {
                "animated": false,
                "id": "823538792249688144",
                "invite": "zY8US2f",
                "name": "BES_Yum",
                "__typename": "Emoji"
            }, {
                "animated": false,
                "id": "823538921950543893",
                "invite": "zY8US2f",
                "name": "BES_Smirk",
                "__typename": "Emoji"
            }, {
                "animated": false,
                "id": "864047419331313664",
                "invite": "zY8US2f",
                "name": "BES_Kanye",
                "__typename": "Emoji"
            }, {
                "animated": false,
                "id": "864062679522345011",
                "invite": "zY8US2f",
                "name": "BES_Dead",
                "__typename": "Emoji"
            }, {
                "animated": false,
                "id": "864062679840063518",
                "invite": "zY8US2f",
                "name": "BES_Angry",
                "__typename": "Emoji"
            }, {
                "animated": false,
                "id": "864062679840063521",
                "invite": "zY8US2f",
                "name": "BES_Eyebrow",
                "__typename": "Emoji"
            }, {
                "animated": false,
                "id": "864062679937056798",
                "invite": "zY8US2f",
                "name": "BES_Confused",
                "__typename": "Emoji"
            }, {
                "animated": false,
                "id": "864062679991320576",
                "invite": "zY8US2f",
                "name": "BES_Confounded",
                "__typename": "Emoji"
            }, {
                "animated": false,
                "id": "864062679991320577",
                "invite": "zY8US2f",
                "name": "BES_Expressionless",
                "__typename": "Emoji"
            }, {
                "animated": false,
                "id": "864062680028807168",
                "invite": "zY8US2f",
                "name": "BES_Disappointed",
                "__typename": "Emoji"
            }, {
                "animated": false,
                "id": "864062680028807171",
                "invite": "zY8US2f",
                "name": "BES_NoMouth",
                "__typename": "Emoji"
            }, {
                "animated": false,
                "id": "864062680238260265",
                "invite": "zY8US2f",
                "name": "BES_Kissing",
                "__typename": "Emoji"
            }, {
                "animated": false,
                "id": "864062680247042059",
                "invite": "zY8US2f",
                "name": "BES_RollingEyes",
                "__typename": "Emoji"
            }, {
                "animated": false,
                "id": "864062680268406784",
                "invite": "zY8US2f",
                "name": "BES_Neutral",
                "__typename": "Emoji"
            }, {
                "animated": false,
                "id": "864062680314413066",
                "invite": "zY8US2f",
                "name": "BES_Frown",
                "__typename": "Emoji"
            }, {
                "animated": false,
                "id": "864062680422416384",
                "invite": "zY8US2f",
                "name": "BES_OwO",
                "__typename": "Emoji"
            }, {
                "animated": false,
                "id": "864062680422416387",
                "invite": "zY8US2f",
                "name": "BES_SobPuddle",
                "__typename": "Emoji"
            }, {
                "animated": false,
                "id": "864062680562139167",
                "invite": "zY8US2f",
                "name": "BES_Sweat",
                "__typename": "Emoji"
            }, {
                "animated": false,
                "id": "864062680653496332",
                "invite": "zY8US2f",
                "name": "BES_Tired",
                "__typename": "Emoji"
            }, {
                "animated": false,
                "id": "864062680661491712",
                "invite": "zY8US2f",
                "name": "BES_Sleepy",
                "__typename": "Emoji"
            }, {
                "animated": false,
                "id": "864062680724668437",
                "invite": "zY8US2f",
                "name": "BES_Sick",
                "__typename": "Emoji"
            }, {
                "animated": false,
                "id": "864062680729124924",
                "invite": "zY8US2f",
                "name": "BES_SlightSmile",
                "__typename": "Emoji"
            }, {
                "animated": false,
                "id": "864062680942641182",
                "invite": "zY8US2f",
                "name": "BES_Upsidedown",
                "__typename": "Emoji"
            }, {
                "animated": false,
                "id": "864062854839795732",
                "invite": "zY8US2f",
                "name": "BES_Derp",
                "__typename": "Emoji"
            }, {
                "animated": false,
                "id": "864062872211292160",
                "invite": "zY8US2f",
                "name": "BES_ZippedMouth",
                "__typename": "Emoji"
            }, {
                "animated": false,
                "id": "864063827195985940",
                "invite": "zY8US2f",
                "name": "BES_Stonks",
                "__typename": "Emoji"
            }, {
                "animated": false,
                "id": "864064102271025162",
                "invite": "zY8US2f",
                "name": "BES_NotStonks",
                "__typename": "Emoji"
            }, {
                "animated": false,
                "id": "874699495147962409",
                "invite": "zY8US2f",
                "name": "BES_CoolRacer",
                "__typename": "Emoji"
            }, {
                "animated": false,
                "id": "875142853003739146",
                "invite": "zY8US2f",
                "name": "BES_Drool",
                "__typename": "Emoji"
            }, {
                "animated": false,
                "id": "875142926236266536",
                "invite": "zY8US2f",
                "name": "BES_Lipbite",
                "__typename": "Emoji"
            }, {
                "animated": false,
                "id": "740643171024765059",
                "invite": "TWtdFpf",
                "name": "GES_Aggressive",
                "__typename": "Emoji"
            }, {
                "animated": false,
                "id": "740643171129884725",
                "invite": "TWtdFpf",
                "name": "GES_Pipe",
                "__typename": "Emoji"
            }, {
                "animated": false,
                "id": "740643171222159445",
                "invite": "TWtdFpf",
                "name": "GES_PingPong",
                "__typename": "Emoji"
            }, {
                "animated": false,
                "id": "740643171276423169",
                "invite": "TWtdFpf",
                "name": "GES_Balloon",
                "__typename": "Emoji"
            }, {
                "animated": false,
                "id": "740643171343794249",
                "invite": "TWtdFpf",
                "name": "GES_Stab",
                "__typename": "Emoji"
            }, {
                "animated": false,
                "id": "740643171352051733",
                "invite": "TWtdFpf",
                "name": "GES_SmolHonk",
                "__typename": "Emoji"
            }, {
                "animated": true,
                "id": "740643171368960102",
                "invite": "TWtdFpf",
                "name": "aGES_Honk",
                "__typename": "Emoji"
            }, {
                "animated": false,
                "id": "740643171419291698",
                "invite": "TWtdFpf",
                "name": "GES_Alert",
                "__typename": "Emoji"
            }, {
                "animated": false,
                "id": "740643171419291799",
                "invite": "TWtdFpf",
                "name": "GES_Gay",
                "__typename": "Emoji"
            }, {
                "animated": false,
                "id": "740643171435806731",
                "invite": "TWtdFpf",
                "name": "GES_Ping",
                "__typename": "Emoji"
            }, {
                "animated": false,
                "id": "740643171460972564",
                "invite": "TWtdFpf",
                "name": "GES_HonkL",
                "__typename": "Emoji"
            }, {
                "animated": true,
                "id": "740643171465429093",
                "invite": "TWtdFpf",
                "name": "aGES_WaddleL",
                "__typename": "Emoji"
            }, {
                "animated": false,
                "id": "740643171469361234",
                "invite": "TWtdFpf",
                "name": "GES_Keys",
                "__typename": "Emoji"
            }, {
                "animated": false,
                "id": "740643171469492251",
                "invite": "TWtdFpf",
                "name": "GES_Goose",
                "__typename": "Emoji"
            }, {
                "animated": true,
                "id": "740643171540664360",
                "invite": "TWtdFpf",
                "name": "aGES_Pepe",
                "__typename": "Emoji"
            }, {
                "animated": false,
                "id": "740643171549052988",
                "invite": "TWtdFpf",
                "name": "GES_Spoon",
                "__typename": "Emoji"
            }, {
                "animated": false,
                "id": "740643171549184161",
                "invite": "TWtdFpf",
                "name": "GES_RunL",
                "__typename": "Emoji"
            }, {
                "animated": false,
                "id": "740643171557572629",
                "invite": "TWtdFpf",
                "name": "GES_HonkR",
                "__typename": "Emoji"
            }, {
                "animated": false,
                "id": "740643171557572731",
                "invite": "TWtdFpf",
                "name": "GES_Think",
                "__typename": "Emoji"
            }, {
                "animated": false,
                "id": "740643171557703832",
                "invite": "TWtdFpf",
                "name": "GES_Pizza",
                "__typename": "Emoji"
            }, {
                "animated": false,
                "id": "740643171591127140",
                "invite": "TWtdFpf",
                "name": "GES_RunR",
                "__typename": "Emoji"
            }, {
                "animated": false,
                "id": "740643171729408093",
                "invite": "TWtdFpf",
                "name": "GES_Knife",
                "__typename": "Emoji"
            }, {
                "animated": true,
                "id": "740643171813556425",
                "invite": "TWtdFpf",
                "name": "aGES_AggressiveHonkR",
                "__typename": "Emoji"
            }, {
                "animated": true,
                "id": "740643172123934770",
                "invite": "TWtdFpf",
                "name": "aGES_Vibing",
                "__typename": "Emoji"
            }, {
                "animated": true,
                "id": "740643172543234090",
                "invite": "TWtdFpf",
                "name": "aGES_AggressiveHonkL",
                "__typename": "Emoji"
            }, {
                "animated": false,
                "id": "740654235653505185",
                "invite": "TWtdFpf",
                "name": "GES_Yes",
                "__typename": "Emoji"
            }, {
                "animated": false,
                "id": "740654235707768883",
                "invite": "TWtdFpf",
                "name": "GES_No",
                "__typename": "Emoji"
            }, {
                "animated": false,
                "id": "740688430467645591",
                "invite": "TWtdFpf",
                "name": "GES_Judgemental",
                "__typename": "Emoji"
            }, {
                "animated": false,
                "id": "740891626892820495",
                "invite": "TWtdFpf",
                "name": "GES_BLMSign",
                "__typename": "Emoji"
            }, {
                "animated": false,
                "id": "740891626892820515",
                "invite": "TWtdFpf",
                "name": "GES_EmptySign",
                "__typename": "Emoji"
            }, {
                "animated": false,
                "id": "740891626947477586",
                "invite": "TWtdFpf",
                "name": "GES_HonkSign",
                "__typename": "Emoji"
            }, {
                "animated": false,
                "id": "740891626997547039",
                "invite": "TWtdFpf",
                "name": "GES_GooseSign",
                "__typename": "Emoji"
            }, {
                "animated": false,
                "id": "740891627010261073",
                "invite": "TWtdFpf",
                "name": "GES_EwSign",
                "__typename": "Emoji"
            }, {
                "animated": false,
                "id": "740891627056529419",
                "invite": "TWtdFpf",
                "name": "GES_WTFSign",
                "__typename": "Emoji"
            }, {
                "animated": false,
                "id": "740891627127570541",
                "invite": "TWtdFpf",
                "name": "GES_WeebSign",
                "__typename": "Emoji"
            }, {
                "animated": false,
                "id": "740901149443358722",
                "invite": "TWtdFpf",
                "name": "GES_HonkNitro",
                "__typename": "Emoji"
            }, {
                "animated": false,
                "id": "740901149468524565",
                "invite": "TWtdFpf",
                "name": "GES_HonkBoost",
                "__typename": "Emoji"
            }, {
                "animated": false,
                "id": "740912377884835969",
                "invite": "TWtdFpf",
                "name": "GES_Soldier",
                "__typename": "Emoji"
            }, {
                "animated": false,
                "id": "740913129491529759",
                "invite": "TWtdFpf",
                "name": "GES_BreathFire",
                "__typename": "Emoji"
            }, {
                "animated": false,
                "id": "740913728412975104",
                "invite": "TWtdFpf",
                "name": "GES_BugleHonk",
                "__typename": "Emoji"
            }, {
                "animated": false,
                "id": "740914821226037280",
                "invite": "TWtdFpf",
                "name": "GES_ComradeHonk",
                "__typename": "Emoji"
            }, {
                "animated": false,
                "id": "740915438011023450",
                "invite": "TWtdFpf",
                "name": "GES_HamShank",
                "__typename": "Emoji"
            }, {
                "animated": false,
                "id": "740919431710113832",
                "invite": "TWtdFpf",
                "name": "GES_Crown",
                "__typename": "Emoji"
            }, {
                "animated": false,
                "id": "740923642833010729",
                "invite": "TWtdFpf",
                "name": "GES_Glock",
                "__typename": "Emoji"
            }, {
                "animated": false,
                "id": "740923643181269105",
                "invite": "TWtdFpf",
                "name": "GES_Newspaper",
                "__typename": "Emoji"
            }, {
                "animated": false,
                "id": "740925385730031698",
                "invite": "TWtdFpf",
                "name": "GES_Bra",
                "__typename": "Emoji"
            }, {
                "animated": true,
                "id": "740930758604226701",
                "invite": "TWtdFpf",
                "name": "aGES_WaddleR",
                "__typename": "Emoji"
            }, {
                "animated": false,
                "id": "740931601336238141",
                "invite": "TWtdFpf",
                "name": "GES_Mask",
                "__typename": "Emoji"
            }, {
                "animated": false,
                "id": "740935957972254873",
                "invite": "TWtdFpf",
                "name": "GES_DeleteThis",
                "__typename": "Emoji"
            }, {
                "animated": false,
                "id": "740936876269109329",
                "invite": "TWtdFpf",
                "name": "GES_CottonCandy",
                "__typename": "Emoji"
            }, {
                "animated": false,
                "id": "741032442525253636",
                "invite": "TWtdFpf",
                "name": "GES_Stonks",
                "__typename": "Emoji"
            }, {
                "animated": false,
                "id": "741032442688962641",
                "invite": "TWtdFpf",
                "name": "GES_Rainbow",
                "__typename": "Emoji"
            }, {
                "animated": false,
                "id": "741032442705608806",
                "invite": "TWtdFpf",
                "name": "GES_WallPeek",
                "__typename": "Emoji"
            }, {
                "animated": true,
                "id": "741032442734837921",
                "invite": "TWtdFpf",
                "name": "aGES_Walking",
                "__typename": "Emoji"
            }, {
                "animated": false,
                "id": "741032442798014594",
                "invite": "TWtdFpf",
                "name": "GES_HeartEyes",
                "__typename": "Emoji"
            }, {
                "animated": true,
                "id": "741032442814791702",
                "invite": "TWtdFpf",
                "name": "aGES_Kek",
                "__typename": "Emoji"
            }, {
                "animated": false,
                "id": "741032442818854972",
                "invite": "TWtdFpf",
                "name": "GES_GoldenGoose",
                "__typename": "Emoji"
            }, {
                "animated": false,
                "id": "741032442818986075",
                "invite": "TWtdFpf",
                "name": "GES_CanadianGoose",
                "__typename": "Emoji"
            }, {
                "animated": false,
                "id": "741032442831569029",
                "invite": "TWtdFpf",
                "name": "GES_Banhammer",
                "__typename": "Emoji"
            }, {
                "animated": false,
                "id": "741032442843889726",
                "invite": "TWtdFpf",
                "name": "GES_AK47",
                "__typename": "Emoji"
            }, {
                "animated": false,
                "id": "741032442852540556",
                "invite": "TWtdFpf",
                "name": "GES_Hibiscus",
                "__typename": "Emoji"
            }, {
                "animated": false,
                "id": "741032442885832815",
                "invite": "TWtdFpf",
                "name": "GES_ArmsWine",
                "__typename": "Emoji"
            }, {
                "animated": false,
                "id": "741032442902741062",
                "invite": "TWtdFpf",
                "name": "GES_Detective",
                "__typename": "Emoji"
            }, {
                "animated": false,
                "id": "741032442948878480",
                "invite": "TWtdFpf",
                "name": "GES_QuestionMark",
                "__typename": "Emoji"
            }, {
                "animated": true,
                "id": "741032443745796197",
                "invite": "TWtdFpf",
                "name": "aGES_Frog",
                "__typename": "Emoji"
            }, {
                "animated": false,
                "id": "741032661598077019",
                "invite": "TWtdFpf",
                "name": "GES_FlameGoose",
                "__typename": "Emoji"
            }, {
                "animated": false,
                "id": "742366602644946945",
                "invite": "TWtdFpf",
                "name": "GES_Glasses",
                "__typename": "Emoji"
            }, {
                "animated": false,
                "id": "742366602720444578",
                "invite": "TWtdFpf",
                "name": "GES_VerifiedBotDev",
                "__typename": "Emoji"
            }, {
                "animated": false,
                "id": "742366602934222909",
                "invite": "TWtdFpf",
                "name": "GES_Clown",
                "__typename": "Emoji"
            }, {
                "animated": false,
                "id": "742366602951000194",
                "invite": "TWtdFpf",
                "name": "GES_Burger",
                "__typename": "Emoji"
            }, {
                "animated": false,
                "id": "742366603110383616",
                "invite": "TWtdFpf",
                "name": "GES_EarlySupporter",
                "__typename": "Emoji"
            }, {
                "animated": false,
                "id": "742366603177361528",
                "invite": "TWtdFpf",
                "name": "GES_JediLightsaber",
                "__typename": "Emoji"
            }, {
                "animated": false,
                "id": "742366603198332995",
                "invite": "TWtdFpf",
                "name": "GES_Hugging",
                "__typename": "Emoji"
            }, {
                "animated": false,
                "id": "742366603231887400",
                "invite": "TWtdFpf",
                "name": "GES_SimpSign",
                "__typename": "Emoji"
            }, {
                "animated": false,
                "id": "742366603244732426",
                "invite": "TWtdFpf",
                "name": "GES_BugHunter",
                "__typename": "Emoji"
            }, {
                "animated": true,
                "id": "742366603261378561",
                "invite": "TWtdFpf",
                "name": "aGES_Demon",
                "__typename": "Emoji"
            }, {
                "animated": false,
                "id": "742366603345395792",
                "invite": "TWtdFpf",
                "name": "GES_TransFlag",
                "__typename": "Emoji"
            }, {
                "animated": false,
                "id": "742366603546591332",
                "invite": "TWtdFpf",
                "name": "GES_Flying",
                "__typename": "Emoji"
            }, {
                "animated": true,
                "id": "742366603789860904",
                "invite": "TWtdFpf",
                "name": "aGES_CowboyRiding",
                "__typename": "Emoji"
            }, {
                "animated": false,
                "id": "742367228976169080",
                "invite": "TWtdFpf",
                "name": "GES_GrandTheftAuto",
                "__typename": "Emoji"
            }, {
                "animated": false,
                "id": "742373003379212418",
                "invite": "TWtdFpf",
                "name": "GES_Bucket",
                "__typename": "Emoji"
            }, {
                "animated": true,
                "id": "748671759070265365",
                "invite": "TWtdFpf",
                "name": "aGES_Poggers",
                "__typename": "Emoji"
            }, {
                "animated": false,
                "id": "748671759171190845",
                "invite": "TWtdFpf",
                "name": "GES_RocketLauncher",
                "__typename": "Emoji"
            }, {
                "animated": false,
                "id": "748671759317991527",
                "invite": "TWtdFpf",
                "name": "GES_Rose",
                "__typename": "Emoji"
            }, {
                "animated": false,
                "id": "748671759368060928",
                "invite": "TWtdFpf",
                "name": "GES_Partner",
                "__typename": "Emoji"
            }, {
                "animated": false,
                "id": "748671759397552228",
                "invite": "TWtdFpf",
                "name": "GES_Pog",
                "__typename": "Emoji"
            }, {
                "animated": false,
                "id": "748671759401746482",
                "invite": "TWtdFpf",
                "name": "GES_DiscordStaff",
                "__typename": "Emoji"
            }, {
                "animated": false,
                "id": "748671759930097754",
                "invite": "TWtdFpf",
                "name": "GES_ChadSouthern",
                "__typename": "Emoji"
            }, {
                "animated": false,
                "id": "748671759942811708",
                "invite": "TWtdFpf",
                "name": "GES_CSGOPimp",
                "__typename": "Emoji"
            }, {
                "animated": false,
                "id": "748671760156590180",
                "invite": "TWtdFpf",
                "name": "GES_PepeHiding",
                "__typename": "Emoji"
            }, {
                "animated": true,
                "id": "748672215691690125",
                "invite": "TWtdFpf",
                "name": "aGES_Cursed",
                "__typename": "Emoji"
            }, {
                "animated": false,
                "id": "748674314139598978",
                "invite": "TWtdFpf",
                "name": "GES_GooseWarning",
                "__typename": "Emoji"
            }, {
                "animated": false,
                "id": "748674983416430642",
                "invite": "TWtdFpf",
                "name": "GES_MLG",
                "__typename": "Emoji"
            }, {
                "animated": false,
                "id": "793959756251398154",
                "invite": "TWtdFpf",
                "name": "GES_Doom",
                "__typename": "Emoji"
            }, {
                "animated": false,
                "id": "820414277349146655",
                "invite": "BFdrpcVr8Z",
                "name": "PC_PopoGa",
                "__typename": "Emoji"
            }, {
                "animated": false,
                "id": "820414403584327701",
                "invite": "BFdrpcVr8Z",
                "name": "PC_PogLuigi",
                "__typename": "Emoji"
            }, {
                "animated": false,
                "id": "820415114208608277",
                "invite": "BFdrpcVr8Z",
                "name": "PC_PogUndelayed",
                "__typename": "Emoji"
            }, {
                "animated": false,
                "id": "820415226641121281",
                "invite": "BFdrpcVr8Z",
                "name": "PC_PogWeird",
                "__typename": "Emoji"
            }, {
                "animated": false,
                "id": "820415324125003856",
                "invite": "BFdrpcVr8Z",
                "name": "PC_PogDelayDistort",
                "__typename": "Emoji"
            }, {
                "animated": false,
                "id": "820415395721773086",
                "invite": "BFdrpcVr8Z",
                "name": "PC_PogDamn",
                "__typename": "Emoji"
            }, {
                "animated": false,
                "id": "820415481646284820",
                "invite": "BFdrpcVr8Z",
                "name": "PC_PogXD",
                "__typename": "Emoji"
            }, {
                "animated": false,
                "id": "820415577570672660",
                "invite": "BFdrpcVr8Z",
                "name": "PC_PogO",
                "__typename": "Emoji"
            }, {
                "animated": false,
                "id": "820415622714228756",
                "invite": "BFdrpcVr8Z",
                "name": "PC_Epog",
                "__typename": "Emoji"
            }, {
                "animated": false,
                "id": "820415773662773249",
                "invite": "BFdrpcVr8Z",
                "name": "PC_PogTooth",
                "__typename": "Emoji"
            }, {
                "animated": false,
                "id": "820415914981457992",
                "invite": "BFdrpcVr8Z",
                "name": "PC_PogDuck",
                "__typename": "Emoji"
            }, {
                "animated": false,
                "id": "820416002969174097",
                "invite": "BFdrpcVr8Z",
                "name": "PC_Pogaroo",
                "__typename": "Emoji"
            }, {
                "animated": true,
                "id": "820416212546748416",
                "invite": "BFdrpcVr8Z",
                "name": "aPC_PogLipsDance",
                "__typename": "Emoji"
            }, {
                "animated": false,
                "id": "820416359300989018",
                "invite": "BFdrpcVr8Z",
                "name": "PC_PogScuffed",
                "__typename": "Emoji"
            }, {
                "animated": false,
                "id": "820416468197441566",
                "invite": "BFdrpcVr8Z",
                "name": "PC_PogCry",
                "__typename": "Emoji"
            }, {
                "animated": false,
                "id": "820416531304546385",
                "invite": "BFdrpcVr8Z",
                "name": "PC_PogT",
                "__typename": "Emoji"
            }, {
                "animated": true,
                "id": "820416633323126836",
                "invite": "BFdrpcVr8Z",
                "name": "aPC_PogMelt",
                "__typename": "Emoji"
            }, {
                "animated": false,
                "id": "820416710389399562",
                "invite": "BFdrpcVr8Z",
                "name": "PC_PogWeirdU",
                "__typename": "Emoji"
            }, {
                "animated": false,
                "id": "820416849568596038",
                "invite": "BFdrpcVr8Z",
                "name": "PC_PogEyU",
                "__typename": "Emoji"
            }, {
                "animated": false,
                "id": "820416920355340339",
                "invite": "BFdrpcVr8Z",
                "name": "PC_PogEyYou",
                "__typename": "Emoji"
            }, {
                "animated": false,
                "id": "820416999448379392",
                "invite": "BFdrpcVr8Z",
                "name": "PC_PogDerpCrying",
                "__typename": "Emoji"
            }, {
                "animated": false,
                "id": "820417142138339349",
                "invite": "BFdrpcVr8Z",
                "name": "PC_PogPepeGa",
                "__typename": "Emoji"
            }, {
                "animated": true,
                "id": "820417255048740964",
                "invite": "BFdrpcVr8Z",
                "name": "aPC_PogTooth",
                "__typename": "Emoji"
            }, {
                "animated": false,
                "id": "820417350889242698",
                "invite": "BFdrpcVr8Z",
                "name": "PC_UnPog",
                "__typename": "Emoji"
            }, {
                "animated": true,
                "id": "820417425203003421",
                "invite": "BFdrpcVr8Z",
                "name": "aPC_PogLips",
                "__typename": "Emoji"
            }, {
                "animated": true,
                "id": "820418154320494632",
                "invite": "BFdrpcVr8Z",
                "name": "aPC_PogSicle",
                "__typename": "Emoji"
            }, {
                "animated": false,
                "id": "820418573851820073",
                "invite": "BFdrpcVr8Z",
                "name": "PC_PogDemon",
                "__typename": "Emoji"
            }, {
                "animated": false,
                "id": "820418667300519967",
                "invite": "BFdrpcVr8Z",
                "name": "PC_PogCabbage",
                "__typename": "Emoji"
            }, {
                "animated": false,
                "id": "820418854332268576",
                "invite": "BFdrpcVr8Z",
                "name": "PC_PogSouless",
                "__typename": "Emoji"
            }, {
                "animated": false,
                "id": "820418974483349535",
                "invite": "BFdrpcVr8Z",
                "name": "PC_PogTeeth",
                "__typename": "Emoji"
            }, {
                "animated": false,
                "id": "820419042560180234",
                "invite": "BFdrpcVr8Z",
                "name": "PC_PogChampion",
                "__typename": "Emoji"
            }, {
                "animated": false,
                "id": "820419262182719500",
                "invite": "BFdrpcVr8Z",
                "name": "PC_PogGrin",
                "__typename": "Emoji"
            }, {
                "animated": true,
                "id": "820419476473249813",
                "invite": "BFdrpcVr8Z",
                "name": "aPC_PogChomp",
                "__typename": "Emoji"
            }, {
                "animated": false,
                "id": "820419543482499113",
                "invite": "BFdrpcVr8Z",
                "name": "PC_PogEyThumbsUp",
                "__typename": "Emoji"
            }, {
                "animated": false,
                "id": "820419595121983549",
                "invite": "BFdrpcVr8Z",
                "name": "PC_PogChamp",
                "__typename": "Emoji"
            }, {
                "animated": false,
                "id": "820419641545195520",
                "invite": "BFdrpcVr8Z",
                "name": "PC_PogEy",
                "__typename": "Emoji"
            }, {
                "animated": false,
                "id": "820419697279238234",
                "invite": "BFdrpcVr8Z",
                "name": "PC_PogPeepo",
                "__typename": "Emoji"
            }, {
                "animated": true,
                "id": "820421628822814771",
                "invite": "BFdrpcVr8Z",
                "name": "aPC_PogChomper",
                "__typename": "Emoji"
            }, {
                "animated": false,
                "id": "820421747584008243",
                "invite": "BFdrpcVr8Z",
                "name": "PC_ReallySadChamp",
                "__typename": "Emoji"
            }, {
                "animated": false,
                "id": "820423488598442004",
                "invite": "BFdrpcVr8Z",
                "name": "PC_PogayaAya",
                "__typename": "Emoji"
            }, {
                "animated": false,
                "id": "820424436473004032",
                "invite": "BFdrpcVr8Z",
                "name": "PC_PogHeartEyes",
                "__typename": "Emoji"
            }, {
                "animated": false,
                "id": "820432166130548746",
                "invite": "BFdrpcVr8Z",
                "name": "PC_MadChamp",
                "__typename": "Emoji"
            }, {
                "animated": false,
                "id": "820609828207984661",
                "invite": "BFdrpcVr8Z",
                "name": "PC_PainChamp",
                "__typename": "Emoji"
            }, {
                "animated": false,
                "id": "820790530895249418",
                "invite": "BFdrpcVr8Z",
                "name": "PC_PogNo",
                "__typename": "Emoji"
            }, {
                "animated": false,
                "id": "820790705663639583",
                "invite": "BFdrpcVr8Z",
                "name": "PC_PogYes",
                "__typename": "Emoji"
            }, {
                "animated": false,
                "id": "820805788347793468",
                "invite": "BFdrpcVr8Z",
                "name": "PC_FlushedChamp",
                "__typename": "Emoji"
            }, {
                "animated": false,
                "id": "820955526304497735",
                "invite": "BFdrpcVr8Z",
                "name": "PC_PogStonks",
                "__typename": "Emoji"
            }, {
                "animated": false,
                "id": "820960178748260352",
                "invite": "BFdrpcVr8Z",
                "name": "PC_SmileChamp",
                "__typename": "Emoji"
            }, {
                "animated": false,
                "id": "820964869015601163",
                "invite": "BFdrpcVr8Z",
                "name": "PC_PogYou",
                "__typename": "Emoji"
            }, {
                "animated": true,
                "id": "820966851777003550",
                "invite": "BFdrpcVr8Z",
                "name": "aPC_PogZoom",
                "__typename": "Emoji"
            }, {
                "animated": false,
                "id": "820969250319499274",
                "invite": "BFdrpcVr8Z",
                "name": "PC_PogJuice",
                "__typename": "Emoji"
            }, {
                "animated": false,
                "id": "820976880223387670",
                "invite": "BFdrpcVr8Z",
                "name": "PC_PogThumpsUp",
                "__typename": "Emoji"
            }, {
                "animated": false,
                "id": "820977219056697395",
                "invite": "BFdrpcVr8Z",
                "name": "PC_CatPog",
                "__typename": "Emoji"
            }, {
                "animated": false,
                "id": "820979923278889040",
                "invite": "BFdrpcVr8Z",
                "name": "PC_PogAnime",
                "__typename": "Emoji"
            }, {
                "animated": false,
                "id": "820980792674484286",
                "invite": "BFdrpcVr8Z",
                "name": "PC_LongChamp",
                "__typename": "Emoji"
            }, {
                "animated": false,
                "id": "820981607212646471",
                "invite": "BFdrpcVr8Z",
                "name": "PC_5Pog",
                "__typename": "Emoji"
            }, {
                "animated": false,
                "id": "820982925519618088",
                "invite": "BFdrpcVr8Z",
                "name": "PC_PissedChamp",
                "__typename": "Emoji"
            }, {
                "animated": false,
                "id": "820983377783422997",
                "invite": "BFdrpcVr8Z",
                "name": "PC_CursedChamp",
                "__typename": "Emoji"
            }, {
                "animated": false,
                "id": "820984093965156393",
                "invite": "BFdrpcVr8Z",
                "name": "PC_PogKnight",
                "__typename": "Emoji"
            }, {
                "animated": false,
                "id": "820985281716944906",
                "invite": "BFdrpcVr8Z",
                "name": "PC_WeerdChamp",
                "__typename": "Emoji"
            }, {
                "animated": false,
                "id": "820985796748115988",
                "invite": "BFdrpcVr8Z",
                "name": "PC_GrossChamp",
                "__typename": "Emoji"
            }, {
                "animated": false,
                "id": "820986358205120512",
                "invite": "BFdrpcVr8Z",
                "name": "PC_HighChamp",
                "__typename": "Emoji"
            }, {
                "animated": false,
                "id": "820987971343745034",
                "invite": "BFdrpcVr8Z",
                "name": "PC_TiredChamp",
                "__typename": "Emoji"
            }, {
                "animated": false,
                "id": "820988954761101322",
                "invite": "BFdrpcVr8Z",
                "name": "PC_PogAngryPoint",
                "__typename": "Emoji"
            }, {
                "animated": true,
                "id": "820994239432622081",
                "invite": "BFdrpcVr8Z",
                "name": "aPC_PogArrive",
                "__typename": "Emoji"
            }, {
                "animated": false,
                "id": "820997143275503667",
                "invite": "BFdrpcVr8Z",
                "name": "PC_PogOwO",
                "__typename": "Emoji"
            }, {
                "animated": false,
                "id": "820998656072482838",
                "invite": "BFdrpcVr8Z",
                "name": "PC_ThanosPog",
                "__typename": "Emoji"
            }, {
                "animated": false,
                "id": "820998831645655040",
                "invite": "BFdrpcVr8Z",
                "name": "PC_PogOff",
                "__typename": "Emoji"
            }, {
                "animated": false,
                "id": "820999455964266507",
                "invite": "BFdrpcVr8Z",
                "name": "PC_SusChamp",
                "__typename": "Emoji"
            }, {
                "animated": true,
                "id": "821000173206503434",
                "invite": "BFdrpcVr8Z",
                "name": "aPC_SmhChamp",
                "__typename": "Emoji"
            }, {
                "animated": false,
                "id": "821000693367701524",
                "invite": "BFdrpcVr8Z",
                "name": "PC_LinusWeirdChamp",
                "__typename": "Emoji"
            }, {
                "animated": false,
                "id": "821000837164826634",
                "invite": "BFdrpcVr8Z",
                "name": "PC_LinusOkayChamp",
                "__typename": "Emoji"
            }, {
                "animated": false,
                "id": "821000964097179669",
                "invite": "BFdrpcVr8Z",
                "name": "PC_CoolChamp",
                "__typename": "Emoji"
            }, {
                "animated": false,
                "id": "821001455703556136",
                "invite": "BFdrpcVr8Z",
                "name": "Pc_PagMan",
                "__typename": "Emoji"
            }, {
                "animated": true,
                "id": "821002129363042364",
                "invite": "BFdrpcVr8Z",
                "name": "aPC_PogBike",
                "__typename": "Emoji"
            }, {
                "animated": false,
                "id": "821002192004841492",
                "invite": "BFdrpcVr8Z",
                "name": "PC_PogU",
                "__typename": "Emoji"
            }, {
                "animated": false,
                "id": "821003650326986825",
                "invite": "BFdrpcVr8Z",
                "name": "PC_HuhChamp",
                "__typename": "Emoji"
            }, {
                "animated": false,
                "id": "821004628203405312",
                "invite": "BFdrpcVr8Z",
                "name": "PC_PensivePog",
                "__typename": "Emoji"
            }, {
                "animated": false,
                "id": "821006062391001138",
                "invite": "BFdrpcVr8Z",
                "name": "PC_CryChamp",
                "__typename": "Emoji"
            }, {
                "animated": false,
                "id": "821015969773256734",
                "invite": "BFdrpcVr8Z",
                "name": "PC_PogGog",
                "__typename": "Emoji"
            }, {
                "animated": false,
                "id": "821016552115011604",
                "invite": "BFdrpcVr8Z",
                "name": "PC_PogGhast",
                "__typename": "Emoji"
            }, {
                "animated": false,
                "id": "821021491876986933",
                "invite": "BFdrpcVr8Z",
                "name": "PC_PogNut",
                "__typename": "Emoji"
            }, {
                "animated": false,
                "id": "821022256485367858",
                "invite": "BFdrpcVr8Z",
                "name": "PC_3Pog",
                "__typename": "Emoji"
            }, {
                "animated": true,
                "id": "821024586824810517",
                "invite": "BFdrpcVr8Z",
                "name": "aPC_Pogception",
                "__typename": "Emoji"
            }, {
                "animated": true,
                "id": "821026684446048337",
                "invite": "BFdrpcVr8Z",
                "name": "aPC_Pogo",
                "__typename": "Emoji"
            }, {
                "animated": false,
                "id": "821028366115012689",
                "invite": "BFdrpcVr8Z",
                "name": "PC_PogDealWithIt",
                "__typename": "Emoji"
            }, {
                "animated": false,
                "id": "821031988982448138",
                "invite": "BFdrpcVr8Z",
                "name": "PC_PogStop",
                "__typename": "Emoji"
            }, {
                "animated": true,
                "id": "821032258097512518",
                "invite": "BFdrpcVr8Z",
                "name": "aPC_PogGiggle",
                "__typename": "Emoji"
            }, {
                "animated": false,
                "id": "821035653658574958",
                "invite": "BFdrpcVr8Z",
                "name": "PC_Pogchungus",
                "__typename": "Emoji"
            }, {
                "animated": false,
                "id": "821035817173647430",
                "invite": "BFdrpcVr8Z",
                "name": "PC_PogGun",
                "__typename": "Emoji"
            }, {
                "animated": false,
                "id": "821037243019427880",
                "invite": "BFdrpcVr8Z",
                "name": "PC_ChomPog",
                "__typename": "Emoji"
            }, {
                "animated": true,
                "id": "821041547461525533",
                "invite": "BFdrpcVr8Z",
                "name": "aPC_PogTongue",
                "__typename": "Emoji"
            }, {
                "animated": true,
                "id": "821088681775464458",
                "invite": "BFdrpcVr8Z",
                "name": "aPC_NodChamp",
                "__typename": "Emoji"
            }, {
                "animated": true,
                "id": "821141034134274068",
                "invite": "BFdrpcVr8Z",
                "name": "aPC_PogJam",
                "__typename": "Emoji"
            }, {
                "animated": false,
                "id": "821141145211633764",
                "invite": "BFdrpcVr8Z",
                "name": "PC_PigChamp",
                "__typename": "Emoji"
            }, {
                "animated": false,
                "id": "821145286381928530",
                "invite": "BFdrpcVr8Z",
                "name": "PC_PogLove",
                "__typename": "Emoji"
            }, {
                "animated": false,
                "id": "821164004264247298",
                "invite": "BFdrpcVr8Z",
                "name": "PC_PogMonkas",
                "__typename": "Emoji"
            }, {
                "animated": false,
                "id": "821164324101685288",
                "invite": "BFdrpcVr8Z",
                "name": "PC_PogChoomp",
                "__typename": "Emoji"
            }, {
                "animated": false,
                "id": "821207732048101446",
                "invite": "BFdrpcVr8Z",
                "name": "PC_PogWhirl",
                "__typename": "Emoji"
            }, {
                "animated": false,
                "id": "821208165906645013",
                "invite": "BFdrpcVr8Z",
                "name": "PC_HyperPog",
                "__typename": "Emoji"
            }, {
                "animated": false,
                "id": "821208289366245418",
                "invite": "BFdrpcVr8Z",
                "name": "PC_HyperPogU",
                "__typename": "Emoji"
            }, {
                "animated": false,
                "id": "821208393201090560",
                "invite": "BFdrpcVr8Z",
                "name": "PC_HyperSuperPog",
                "__typename": "Emoji"
            }, {
                "animated": false,
                "id": "821219510891577385",
                "invite": "BFdrpcVr8Z",
                "name": "PC_PogGrog",
                "__typename": "Emoji"
            }, {
                "animated": false,
                "id": "821349381625872394",
                "invite": "BFdrpcVr8Z",
                "name": "PC_PogChumb",
                "__typename": "Emoji"
            }, {
                "animated": false,
                "id": "821354304634880032",
                "invite": "BFdrpcVr8Z",
                "name": "PC_PogVR",
                "__typename": "Emoji"
            }, {
                "animated": false,
                "id": "821355207853080578",
                "invite": "BFdrpcVr8Z",
                "name": "PC_OmegaPog",
                "__typename": "Emoji"
            }, {
                "animated": false,
                "id": "821355313370365982",
                "invite": "BFdrpcVr8Z",
                "name": "PC_PogChunky",
                "__typename": "Emoji"
            }, {
                "animated": true,
                "id": "821358212187422771",
                "invite": "BFdrpcVr8Z",
                "name": "aPC_PogUShake",
                "__typename": "Emoji"
            }, {
                "animated": true,
                "id": "821358292306493481",
                "invite": "BFdrpcVr8Z",
                "name": "aPc_PogPat",
                "__typename": "Emoji"
            }, {
                "animated": false,
                "id": "821359410991333376",
                "invite": "BFdrpcVr8Z",
                "name": "PC_BaldChamp",
                "__typename": "Emoji"
            }, {
                "animated": true,
                "id": "821360731513290792",
                "invite": "BFdrpcVr8Z",
                "name": "aPC_InsaneChampNod",
                "__typename": "Emoji"
            }, {
                "animated": false,
                "id": "821360830611325008",
                "invite": "BFdrpcVr8Z",
                "name": "PC_Poggies",
                "__typename": "Emoji"
            }, {
                "animated": false,
                "id": "821374982907101194",
                "invite": "BFdrpcVr8Z",
                "name": "PC_PogKidnapped",
                "__typename": "Emoji"
            }, {
                "animated": false,
                "id": "821378865045307482",
                "invite": "BFdrpcVr8Z",
                "name": "PC_PogSwirl",
                "__typename": "Emoji"
            }, {
                "animated": false,
                "id": "821379725552386118",
                "invite": "BFdrpcVr8Z",
                "name": "PC_PogBigNose",
                "__typename": "Emoji"
            }, {
                "animated": true,
                "id": "821382930110742538",
                "invite": "BFdrpcVr8Z",
                "name": "aPC_PogCatPat",
                "__typename": "Emoji"
            }, {
                "animated": false,
                "id": "821385986909929472",
                "invite": "BFdrpcVr8Z",
                "name": "PC_PogPeek",
                "__typename": "Emoji"
            }, {
                "animated": true,
                "id": "821444541822795797",
                "invite": "BFdrpcVr8Z",
                "name": "aPC_WeirdButOkay",
                "__typename": "Emoji"
            }, {
                "animated": false,
                "id": "821449766004719667",
                "invite": "BFdrpcVr8Z",
                "name": "PC_PogXog",
                "__typename": "Emoji"
            }, {
                "animated": false,
                "id": "821450054140166246",
                "invite": "BFdrpcVr8Z",
                "name": "PC_PogBigBrain",
                "__typename": "Emoji"
            }, {
                "animated": false,
                "id": "821469126085181451",
                "invite": "BFdrpcVr8Z",
                "name": "PC_PauseChamp",
                "__typename": "Emoji"
            }, {
                "animated": false,
                "id": "827227827987677224",
                "invite": "BFdrpcVr8Z",
                "name": "PC_PogChap",
                "__typename": "Emoji"
            }
        ]
    }
}
